{"data": [{"title": "Aven Colony", "id": 484900, "initial": 2999, "final": 749, "discount": 75}, {"title": "BATTLETECH", "id": 637090, "initial": 3999, "final": 999, "discount": 75}, {"title": "Bee Simulator", "id": 914750, "initial": 2999, "final": 1049, "discount": 65}, {"title": "Black Book", "id": 1138660, "initial": 2499, "final": 1674, "discount": 33}, {"title": "Car Mechanic Simulator 2015", "id": 320300, "initial": 1999, "final": 199, "discount": 90}, {"title": "Car Mechanic Simulator 2018", "id": 645630, "initial": 1999, "final": 659, "discount": 67}, {"title": "Car Mechanic Simulator 2021", "id": 1190000, "initial": 2099, "final": 1889, "discount": 10}, {"title": "Castle Flipper", "id": 944250, "initial": 1599, "final": 639, "discount": 60}, {"title": "Cris Tales", "id": 1079830, "initial": 3999, "final": 1999, "discount": 50}, {"title": "Crown Trick", "id": 1000010, "initial": 1999, "final": 799, "discount": 60}, {"title": "CyberTaxi", "id": 1420850, "initial": 819, "final": 81, "discount": 90}, {"title": "Danger Scavenger", "id": 1169740, "initial": 819, "final": 204, "discount": 75}, {"title": "Deadliest Catch: The Game", "id": 838630, "initial": 1679, "final": 251, "discount": 85}, {"title": "Dead Cells", "id": 588650, "initial": 2499, "final": 1249, "discount": 50}, {"title": "Driftland: The Magic Revival", "id": 718650, "initial": 1699, "final": 169, "discount": 90}, {"title": "Endzone - A World Apart", "id": 933820, "initial": 2999, "final": 1499, "discount": 50}, {"title": "Genesis Alpha One Deluxe Edition", "id": 712190, "initial": 2799, "final": 699, "discount": 75}, {"title": "Greak: Memories of Azur", "id": 1311070, "initial": 1999, "final": 1199, "discount": 40}, {"title": "Just Die Already", "id": 979070, "initial": 1399, "final": 629, "discount": 55}, {"title": "Magicka 2", "id": 238370, "initial": 1499, "final": 374, "discount": 75}, {"title": "Main Assembly", "id": 1078920, "initial": 1999, "final": 799, "discount": 60}, {"title": "Maneater", "id": 629820, "initial": 3399, "final": 2039, "discount": 40}, {"title": "MetaMorph: Dungeon Creatures", "id": 606870, "initial": 819, "final": 573, "discount": 30}, {"title": "Monster Sanctuary", "id": 814370, "initial": 1999, "final": 679, "discount": 66}, {"title": "MXGP 2021 - The Official Motocross Videogame", "id": 1610470, "initial": 4999, "final": 3499, "discount": 30}, {"title": "My Time At Portia", "id": 666140, "initial": 2999, "final": 749, "discount": 75}, {"title": "Narita Boy", "id": 1069530, "initial": 2499, "final": 1249, "discount": 50}, {"title": "Nine Parchments", "id": 471550, "initial": 1999, "final": 499, "discount": 75}, {"title": "Oriental Empires", "id": 357310, "initial": 2799, "final": 559, "discount": 80}, {"title": "Severed Steel", "id": 1227690, "initial": 2099, "final": 1574, "discount": 25}, {"title": "Sheltered", "id": 356040, "initial": 1299, "final": 324, "discount": 75}, {"title": "Snooker 19", "id": 887800, "initial": 3499, "final": 1224, "discount": 65}, {"title": "Space Colony: Steam Edition", "id": 297920, "initial": 1249, "final": 312, "discount": 75}, {"title": "Space Haven", "id": 979110, "initial": 2199, "final": 1473, "discount": 33}, {"title": "SpongeBob SquarePants: Battle for Bikini Bottom - Rehydrated", "id": 969990, "initial": 2999, "final": 989, "discount": 67}, {"title": "Starbase", "id": 454120, "initial": 3299, "final": 2309, "discount": 30}, {"title": "Strategic Mind: Blitzkrieg", "id": 1200330, "initial": 3399, "final": 2209, "discount": 35}, {"title": "Strategic Mind: Fight for Freedom", "id": 1381850, "initial": 2499, "final": 1874, "discount": 25}, {"title": "Strategic Mind: Spectre of Communism", "id": 1341170, "initial": 2499, "final": 1749, "discount": 30}, {"title": "Strategic Mind: The Pacific", "id": 991810, "initial": 2499, "final": 1499, "discount": 40}, {"title": "Stronghold 2: Steam Edition", "id": 40960, "initial": 1249, "final": 312, "discount": 75}, {"title": "Stronghold 3 Gold", "id": 47400, "initial": 2499, "final": 624, "discount": 75}, {"title": "Stronghold Crusader 2", "id": 232890, "initial": 3399, "final": 339, "discount": 90}, {"title": "Stronghold Crusader HD", "id": 40970, "initial": 799, "final": 159, "discount": 80}, {"title": "Stronghold HD", "id": 40950, "initial": 399, "final": 99, "discount": 75}, {"title": "Stronghold Legends: Steam Edition", "id": 40980, "initial": 1249, "final": 374, "discount": 70}, {"title": "Stronghold: Warlords", "id": 907650, "initial": 3499, "final": 1749, "discount": 50}, {"title": "Tales of the Neon Sea", "id": 828740, "initial": 1399, "final": 699, "discount": 50}, {"title": "Thief Simulator", "id": 704850, "initial": 1999, "final": 599, "discount": 70}, {"title": "Trine Enchanted Edition", "id": 35700, "initial": 1499, "final": 374, "discount": 75}, {"title": "Trine 2: Complete Story", "id": 35720, "initial": 1999, "final": 499, "discount": 75}, {"title": "Trine 4: The Nightmare Prince", "id": 690640, "initial": 2999, "final": 749, "discount": 75}, {"title": "UBOAT", "id": 494840, "initial": 2499, "final": 1049, "discount": 58}, {"title": "Ultimate Fishing Simulator", "id": 468920, "initial": 1999, "final": 499, "discount": 75}, {"title": "Vikings - Wolves of Midgard", "id": 404590, "initial": 2999, "final": 1019, "discount": 66}, {"title": "The Wild Eight", "id": 526160, "initial": 2499, "final": 749, "discount": 70}, {"title": "Worms Armageddon", "id": 217200, "initial": 1499, "final": 299, "discount": 80}, {"title": "Worms Clan Wars", "id": 233840, "initial": 2299, "final": 459, "discount": 80}, {"title": "Worms Reloaded", "id": 22600, "initial": 2299, "final": 459, "discount": 80}, {"title": "Worms Rumble", "id": 1186040, "initial": 1499, "final": 374, "discount": 75}, {"title": "Yooka-Laylee", "id": 360830, "initial": 4999, "final": 999, "discount": 80}]}